grid_strategy/__init__.py
grid_strategy/_abc.py
grid_strategy/strategies.py
grid_strategy-0.0.1.dist-info/LICENSE
grid_strategy-0.0.1.dist-info/METADATA
grid_strategy-0.0.1.dist-info/WHEEL
grid_strategy-0.0.1.dist-info/top_level.txt
grid_strategy-0.0.1.dist-info/RECORD
