Metadata-Version: 2.1
Name: grid-strategy
Version: 0.0.1
Summary: A package for organizing matplotlib plots.
Home-page: https://github.com/matplotlib/grid-strategy
Author: Grid Strategy Authors
Author-email: paul@ganssle.io
License: Apache License 2.0
Platform: UNKNOWN
Classifier: Intended Audience :: Science/Research
Classifier: License :: OSI Approved :: Python Software Foundation License
Classifier: Programming Language :: Python
Classifier: Programming Language :: Python :: 3
Classifier: Programming Language :: Python :: 3.6
Classifier: Programming Language :: Python :: 3.7
Classifier: Topic :: Scientific/Engineering :: Visualization
Requires-Python: >=3.6
Requires-Dist: matplotlib
Requires-Dist: numpy
